airfoil_db/__init__.py
airfoil_db/airfoil.py
airfoil_db/exceptions.py
airfoil_db/poly_fits.py
airfoil_db-1.4.3.dist-info/licenses/LICENSE
airfoil_db-1.4.3.dist-info/METADATA
airfoil_db-1.4.3.dist-info/WHEEL
airfoil_db-1.4.3.dist-info/top_level.txt
airfoil_db-1.4.3.dist-info/RECORD
