Metadata-Version: 2.4
Name: airfoil_db
Version: 1.4.3
Summary: A Fork for web wrapper of MachupX using AirfoilDatabase. A Python module for modeling airfoils using Xfoil.
Home-page: https://github.com/usuaero/AirfoilDatabase
Author: usuaero
Author-email: doug.hunsaker@usu.edu
License: MIT
Requires-Python: >=3.6.0
License-File: LICENSE
Requires-Dist: numpy
Requires-Dist: scipy
Requires-Dist: matplotlib
Dynamic: author
Dynamic: author-email
Dynamic: home-page
Dynamic: license
Dynamic: license-file
Dynamic: requires-dist
Dynamic: requires-python
Dynamic: summary
